[{"name":"start_processing.action_controller","payload":{"controller":"Devise::RegistrationsController","action":"create","params":{"utf8":"\u2713","authenticity_token":"JVNe9lufM630Jr4hf8wMGQvoCtnQnULTgZxa3uPmGDU=","user":{"email":"user@gmail.com","password":"[FILTERED]","password_confirmation":"[FILTERED]"},"commit":"Sign up","action":"create","controller":"devise/registrations"},"format":"html","method":"POST","path":"/users"},"time":"2013-02-27T21:38:52-03:00","transaction_id":"148bb13e5c7030dbf449","end":"2013-02-27T21:38:52-03:00","duration":0.002098},{"name":"redirect_to.action_controller","payload":{"status":302,"location":"http://localhost:3000/"},"time":"2013-02-27T21:38:52-03:00","transaction_id":"148bb13e5c7030dbf449","end":"2013-02-27T21:38:52-03:00","duration":0.092266},{"name":"process_action.action_controller","payload":{"controller":"Devise::RegistrationsController","action":"create","params":{"utf8":"\u2713","authenticity_token":"JVNe9lufM630Jr4hf8wMGQvoCtnQnULTgZxa3uPmGDU=","user":{"email":"user@gmail.com","password":"[FILTERED]","password_confirmation":"[FILTERED]"},"commit":"Sign up","action":"create","controller":"devise/registrations"},"format":"html","method":"POST","path":"/users","status":302,"view_runtime":null},"time":"2013-02-27T21:38:52-03:00","transaction_id":"148bb13e5c7030dbf449","end":"2013-02-27T21:38:52-03:00","duration":92.451353}]